{"is_source_file": true, "format": "JavaScript", "description": "This file provides utility functions for safe JSON parsing and managing data in localStorage with a specific namespace, including getItem, setItem, and removeItem functions for the notes application.", "external_files": ["window.localStorage"], "external_methods": ["JSON.parse", "JSON.stringify", "window.localStorage.getItem", "window.localStorage.setItem", "window.localStorage.removeItem"], "published": ["getItem", "setItem", "removeItem"], "classes": [], "methods": [{"name": "safeParse(json, fallback)", "description": "Safely parses JSON string, returning a fallback value if parsing fails.", "scope": "", "scopeKind": ""}, {"name": "getItem(key, fallback = null)", "description": "Retrieves a value from localStorage under the notes_app_v1 namespace and parses it safely.", "scope": "", "scopeKind": ""}, {"name": "setItem(key, value)", "description": "Stores a value in localStorage under the notes_app_v1 namespace after serializing it to JSON.", "scope": "", "scopeKind": ""}, {"name": "removeItem(key)", "description": "Removes a value from localStorage under the notes_app_v1 namespace.", "scope": "", "scopeKind": ""}], "calls": ["JSON.parse", "JSON.stringify", "window.localStorage.getItem", "window.localStorage.setItem", "window.localStorage.removeItem"], "search-terms": ["storage", "localStorage", "js utility", "namespace", "JSON parsing"], "state": 2, "file_id": 15, "knowledge_revision": 32, "git_revision": "", "ctags": [{"_type": "tag", "name": "NS", "path": "/home/kavia/workspace/code-generation/note-manager-214625-214634/notes_frontend/src/utils/storage.js", "pattern": "/^const NS = \"notes_app_v1\";$/", "language": "JavaScript", "kind": "constant"}, {"_type": "tag", "name": "getItem", "path": "/home/kavia/workspace/code-generation/note-manager-214625-214634/notes_frontend/src/utils/storage.js", "pattern": "/^export function getItem(key, fallback = null) {$/", "language": "JavaScript", "kind": "function", "signature": "(key, fallback = null)"}, {"_type": "tag", "name": "removeItem", "path": "/home/kavia/workspace/code-generation/note-manager-214625-214634/notes_frontend/src/utils/storage.js", "pattern": "/^export function removeItem(key) {$/", "language": "JavaScript", "kind": "function", "signature": "(key)"}, {"_type": "tag", "name": "safeParse", "path": "/home/kavia/workspace/code-generation/note-manager-214625-214634/notes_frontend/src/utils/storage.js", "pattern": "/^function safeParse(json, fallback) {$/", "language": "JavaScript", "kind": "function", "signature": "(json, fallback)"}, {"_type": "tag", "name": "setItem", "path": "/home/kavia/workspace/code-generation/note-manager-214625-214634/notes_frontend/src/utils/storage.js", "pattern": "/^export function setItem(key, value) {$/", "language": "JavaScript", "kind": "function", "signature": "(key, value)"}], "hash": "36b412aff16758190e76cf57155799c1", "format-version": 4, "code-base-name": "notes_frontend", "filename": "notes_frontend/src/utils/storage.js", "revision_history": [{"32": ""}]}